patter/__init__.py
patter/exceptions.py
patter/patter.py
patter-0.2.1.data/scripts/patter
patter-0.2.1.dist-info/METADATA
patter-0.2.1.dist-info/RECORD
patter-0.2.1.dist-info/WHEEL
patter-0.2.1.dist-info/top_level.txt
