Metadata-Version: 2.1
Name: patter
Version: 0.2.1
Summary: Pipe stdout directly to Mattermost channels or users.
Home-page: https://github.com/brodan/patter
Author: Christopher Hranj
Author-email: christopher.hranj@gmail.com
License: MIT
Keywords: patter mattermost
Platform: UNKNOWN
Classifier: Development Status :: 3 - Alpha
Classifier: Intended Audience :: Developers
Classifier: License :: OSI Approved :: MIT License
Classifier: Programming Language :: Python
Classifier: Topic :: Communications :: Chat
Classifier: Topic :: Utilities
Requires-Dist: mattermostdriver (>=5.0.0)
